program_writing_assistant/__init__.py
program_writing_assistant/core.py
program_writing_assistant/log.py
program_writing_assistant/server.py
program_writing_assistant-0.1.4.dist-info/METADATA
program_writing_assistant-0.1.4.dist-info/WHEEL
program_writing_assistant-0.1.4.dist-info/top_level.txt
program_writing_assistant-0.1.4.dist-info/RECORD
