Metadata-Version: 2.4
Name: program-writing-assistant
Version: 0.1.4
Summary: Add your description here
Requires-Python: >=3.10
Requires-Dist: llmada>=1.0.5
Requires-Dist: toml==0.10.2
